gbp_purge-1.0.2.dist-info/METADATA
gbp_purge-1.0.2.dist-info/WHEEL
gbp_purge-1.0.2.dist-info/entry_points.txt
gbp_purge/__init__.py
gbp_purge/django/__init__.py
gbp_purge/django/gbp_purge/__init__.py
gbp_purge/django/gbp_purge/apps.py
gbp_purge/django/gbp_purge/models.py
gbp_purge/gateway.py
gbp_purge/purger.py
gbp_purge/py.typed
gbp_purge/signals.py
gbp_purge/types.py
gbp_purge/worker/__init__.py
gbp_purge/worker/tasks.py
gbp_purge-1.0.2.dist-info/RECORD
