Metadata-Version: 2.1
Name: gbp-purge
Version: 1.0.2
Summary: Purge old builds from Gentoo Build Publisher
Author-Email: Albert Hopkins <marduk@letterboxes.org>
License: GPL3+
Project-URL: homepage, https://github.com/enku/gbp-purge
Project-URL: repository, https://github.com/enku/gbp-purge
Requires-Python: >=3.11
Requires-Dist: gentoo-build-publisher>=2.4.0rc1
